src/dictionary_mapper/__about__.py
src/dictionary_mapper/py.typed
dictionary_mapper-0.3.0.dist-info/METADATA
dictionary_mapper-0.3.0.dist-info/WHEEL
dictionary_mapper-0.3.0.dist-info/licenses/LICENSE.txt
dictionary_mapper-0.3.0.dist-info/RECORD
