Metadata-Version: 2.4
Name: dictionary-mapper
Version: 0.3.0
Summary: A tool for mapping and transforming dictionaries based on predefined rules.
Project-URL: Documentation, https://github.com/jjalvarezl-python/dictionary-mapper#readme
Project-URL: Issues, https://github.com/jjalvarezl-python/dictionary-mapper/issues
Project-URL: Source, https://github.com/jjalvarezl-python/dictionary-mapper
Author-email: Jhon Alvarez <jjalvarezl@unicauca.edu.co>
License-Expression: MIT
License-File: LICENSE.txt
Classifier: Development Status :: 4 - Beta
Classifier: Programming Language :: Python
Classifier: Programming Language :: Python :: 3.8
Classifier: Programming Language :: Python :: 3.9
Classifier: Programming Language :: Python :: 3.10
Classifier: Programming Language :: Python :: 3.11
Classifier: Programming Language :: Python :: 3.12
Classifier: Programming Language :: Python :: 3.13
Classifier: Programming Language :: Python :: Implementation :: CPython
Classifier: Programming Language :: Python :: Implementation :: PyPy
Requires-Python: >=3.8
Requires-Dist: anyio>=4.11.0
Requires-Dist: certifi>=2025.10.5
Requires-Dist: cffi>=2.0.0
Requires-Dist: click>=8.3.0
Requires-Dist: cryptography>=46.0.3
Requires-Dist: filelock>=3.20.0
Requires-Dist: httpcore>=1.0.9
Requires-Dist: httpx>=0.28.1
Requires-Dist: idna>=3.11
Requires-Dist: sniffio>=1.3.1
Requires-Dist: zstandard>=0.25.0
Provides-Extra: dev
Requires-Dist: commitizen>=3.27.0; extra == 'dev'
Requires-Dist: coverage>=7.3.3; extra == 'dev'
Requires-Dist: hatch>=1.15.1; extra == 'dev'
Requires-Dist: hatchling>=1.27.0; extra == 'dev'
Requires-Dist: mypy>=1.18.2; extra == 'dev'
Requires-Dist: pre-commit>=4.4.0; extra == 'dev'
Requires-Dist: pytest>=9.0.0; extra == 'dev'
Requires-Dist: rich>=14.2.0; extra == 'dev'
Requires-Dist: ruff>=0.14.4; extra == 'dev'
Requires-Dist: typing-extensions>=4.15.0; extra == 'dev'
